crossplane/function/__version__.py
crossplane/function/logging.py
crossplane/function/py.typed
crossplane/function/request.py
crossplane/function/resource.py
crossplane/function/response.py
crossplane/function/runtime.py
crossplane/function/proto/v1/run_function.proto
crossplane/function/proto/v1/run_function_pb2.py
crossplane/function/proto/v1/run_function_pb2.pyi
crossplane/function/proto/v1/run_function_pb2_grpc.py
crossplane/function/proto/v1beta1/run_function.proto
crossplane/function/proto/v1beta1/run_function_pb2.py
crossplane/function/proto/v1beta1/run_function_pb2.pyi
crossplane/function/proto/v1beta1/run_function_pb2_grpc.py
crossplane_function_sdk_python-0.9.0.dist-info/METADATA
crossplane_function_sdk_python-0.9.0.dist-info/WHEEL
crossplane_function_sdk_python-0.9.0.dist-info/licenses/LICENSE
crossplane_function_sdk_python-0.9.0.dist-info/RECORD
