Metadata-Version: 2.4
Name: crossplane-function-sdk-python
Version: 0.9.0
Summary: The Python SDK for Crossplane composition functions
Project-URL: Documentation, https://github.com/crossplane/function-sdk-python#readme
Project-URL: Issues, https://github.com/crossplane/function-sdk-python/issues
Project-URL: Source, https://github.com/crossplane/function-sdk-python
Author-email: Crossplane Maintainers <info@crossplane.io>
License-Expression: Apache-2.0
License-File: LICENSE
Classifier: Development Status :: 4 - Beta
Classifier: Programming Language :: Python
Classifier: Programming Language :: Python :: 3.11
Classifier: Typing :: Typed
Requires-Python: >=3.11
Requires-Dist: grpcio-reflection==1.*
Requires-Dist: grpcio==1.74.0
Requires-Dist: protobuf==6.31.1
Requires-Dist: pydantic==2.*
Requires-Dist: structlog==25.*
